jsignature/__init__.py
jsignature/fields.py
jsignature/forms.py
jsignature/mixins.py
jsignature/models.py
jsignature/settings.py
jsignature/utils.py
jsignature/widgets.py
jsignature/locale/fr/LC_MESSAGES/django.mo
jsignature/static/js/django_jsignature.js
jsignature/static/js/jSignature.min.js
jsignature/static/js/jsignature_admin_init.js
jsignature/templates/jsignature/widget.html
jsignature/templatetags/__init__.py
jsignature/templatetags/jsignature_filters.py
django_jsignature-0.12.dist-info/LICENSE
django_jsignature-0.12.dist-info/METADATA
django_jsignature-0.12.dist-info/WHEEL
django_jsignature-0.12.dist-info/top_level.txt
django_jsignature-0.12.dist-info/RECORD
