Metadata-Version: 2.1
Name: django-jsignature
Version: 0.12
Summary: Use jSignature jQuery plugin in your django projects
Home-page: https://github.com/fle/django-jsignature
Download-URL: http://pypi.python.org/pypi/django-jsignature
Author: Florent Lebreton
Author-email: florent.lebreton@makina-corpus.com
License: LPGL, see LICENSE file.
Classifier: Topic :: Utilities
Classifier: Natural Language :: English
Classifier: Operating System :: OS Independent
Classifier: Intended Audience :: Developers
Classifier: Environment :: Web Environment
Classifier: Framework :: Django
Classifier: Framework :: Django :: 4.2
Classifier: Framework :: Django :: 5.0
Classifier: Development Status :: 5 - Production/Stable
Classifier: Programming Language :: Python
Classifier: Programming Language :: Python :: 3
Classifier: Programming Language :: Python :: 3.8
Classifier: Programming Language :: Python :: 3.9
Classifier: Programming Language :: Python :: 3.10
Classifier: Programming Language :: Python :: 3.11
Classifier: Programming Language :: Python :: 3.12
License-File: LICENSE
Requires-Dist: Django >=4.2
Requires-Dist: pillow
Requires-Dist: pyquery >=1.4.2
